pyramid_opentracing/__init__.py
pyramid_opentracing/tests.py
pyramid_opentracing/tracer.py
pyramid_opentracing/tween_factory.py
pyramid_opentracing-0.1.0.dist-info/DESCRIPTION.rst
pyramid_opentracing-0.1.0.dist-info/METADATA
pyramid_opentracing-0.1.0.dist-info/metadata.json
pyramid_opentracing-0.1.0.dist-info/RECORD
pyramid_opentracing-0.1.0.dist-info/top_level.txt
pyramid_opentracing-0.1.0.dist-info/WHEEL
