Metadata-Version: 2.0
Name: pyramid-opentracing
Version: 0.1.0
Summary: OpenTracing support for Pyramid applications
Home-page: https://github.com/carlosalberto/python-pyramid/
Author: Carlos Alberto Cortez
Author-email: calberto.cortez@gmail.com
License: BSD
Download-URL: https://github.com/carlosalberto/python-pyramid/tarball/0.1.0
Requires-Dist: pyramid
Requires-Dist: opentracing (>=1.1,<1.2)
